setup.py
flask_miracle/__init__.py
flask_miracle/base.py
flask_miracle/decorators.py
flask_miracle/functions.py
flask_miracle_acl.egg-info/PKG-INFO
flask_miracle_acl.egg-info/SOURCES.txt
flask_miracle_acl.egg-info/dependency_links.txt
flask_miracle_acl.egg-info/requires.txt
flask_miracle_acl.egg-info/top_level.txt