Metadata-Version: 1.1
Name: flask-miracle-acl
Version: 0.2
Summary: The fabric between the Flask framework and Miracle ACL
Home-page: https://github.com/tdpsk/flask-miracle-acl
Author: Timo "tdpsk" Puschkasch
Author-email: timo@puschkasch.com
License: BSD
Platform: any
Classifier: Framework :: Flask
Classifier: Programming Language :: Python :: 2.7
Classifier: Programming Language :: Python :: 3.6
Classifier: License :: OSI Approved :: BSD License
